{"name":"hexo","slug":"hexo","count":1,"postlist":[{"title":"图片预览测试","uid":"7f80b061737ea7e5a386a4ed5419f7bf","slug":"图片预览测试","date":"2022-10-31T07:32:59.000Z","updated":"2022-10-31T07:48:34.503Z","comments":true,"path":"api/articles/图片预览测试.json","keywords":null,"cover":[],"text":"图片预览测试因为插入本地图片的时候发现，本地预览不可用，来试试上传的情况 typora可以预览然而本地生成预览不了 img插件貌似不顶用啊，还得是&lt;img&gt;好使 img插件测试(不加入目录)[typora间歇性可预览]{本地预览不通过}❌ img插件测试(加入目录)[...","link":"","photos":[],"count_time":{"symbolsCount":203,"symbolsTime":"1 mins."},"categories":[],"tags":[{"name":"hexo","slug":"hexo","count":1,"path":"api/tags/hexo.json"}],"author":{"name":"Muzi","slug":"blog-author","avatar":"/images/avatar.png","link":"/","description":"记录点滴生活","socials":{"github":"","twitter":"","stackoverflow":"","wechat":"","qq":"","weibo":"","zhihu":"","csdn":"","juejin":"","customs":{}}},"feature":true}]}